{
  "unpublishedPage": {
    "name": "Client_Billing_Statement",
    "slug": "client-billing-statement",
    "layouts": [
      {
        "viewMode": false,
        "dsl": {
          "widgetName": "MainContainer",
          "backgroundColor": "none",
          "rightColumn": 1224,
          "snapColumns": 64,
          "detachFromLayout": true,
          "widgetId": "0",
          "topRow": 0,
          "bottomRow": 500,
          "containerStyle": "none",
          "snapRows": 63,
          "parentRowSpace": 1,
          "type": "CANVAS_WIDGET",
          "canExtend": true,
          "version": 87,
          "minHeight": 650,
          "parentColumnSpace": 1,
          "dynamicBindingPathList": [],
          "leftColumn": 0
        },
        "layoutOnLoadActions": [
          [
            {
              "id": "Client_Billing_Statement_get_client_bs",
              "name": "get_client_bs",
              "confirmBeforeExecute": false,
              "pluginType": "API",
              "jsonPathKeys": [
                "client_id_input.text"
              ],
              "timeoutInMillisecond": 10000
            }
          ]
        ],
        "layoutOnLoadActionErrors": [],
        "validOnPageLoadActions": true,
        "id": "Client_Billing_Statement",
        "deleted": false,
        "policies": [],
        "userPermissions": []
      }
    ],
    "userPermissions": [],
    "policies": [],
    "isHidden": false
  },
  "deleted": false,
  "gitSyncId": "656e912da17e695e8c0e61ab_656e99fba17e695e8c0e61c5"
}